[{"type":"page","id":"index","valueView":153},{"type":"page","id":"stats","valueView":78},{"type":"utils","id":"cps-tester","valueView":6},{"type":"utils","id":"ja-kana-quiz","valueView":4},{"type":"utils","id":"countdown","valueView":8},{"type":"utils","id":"mc-color-gen","valueView":6},{"type":"utils","id":"touhou-char-moe","valueView":7},{"type":"utils","id":"uuid-gen","valueView":19},{"type":"utils","id":"spg","valueView":99},{"type":"utils","id":"rand-gen","valueView":58},{"type":"utils","id":"bpm-tapper","valueView":111}]